vlive/__init__.py
vlive/channel.py
vlive/models/__init__.py
vlive/models/channel.py
vlive/models/channel_profile.py
vlive/search.py
vlive/session/__init__.py
vlive/session/config.py
vlive/urlpath.py
vlive-0.1.1.dist-info/LICENSE
vlive-0.1.1.dist-info/WHEEL
vlive-0.1.1.dist-info/METADATA
vlive-0.1.1.dist-info/RECORD
